blame_g-0.1.1.dist-info/licenses/LICENSE
src/__init__.py
src/cli.py
blame_g-0.1.1.dist-info/METADATA
blame_g-0.1.1.dist-info/WHEEL
blame_g-0.1.1.dist-info/entry_points.txt
blame_g-0.1.1.dist-info/top_level.txt
blame_g-0.1.1.dist-info/RECORD
