Metadata-Version: 2.4
Name: blame-g
Version: 0.1.1
Summary: blame-g is a command-line tool that analyzes git repositories and generates contributor statistics — including commits, lines added/deleted, files changed, pull requests, reverts, and more — beautifully rendered in a terminal table.
Author-email: Mohammed Muzammil Anwar <mohammad.muzammil100@gmail.com>
License: MIT License
Project-URL: homepage, https://github.com/mcking-07/blame-g
Project-URL: repository, https://github.com/mcking-07/blame-g
Project-URL: documentation, https://github.com/mcking-07/blame-g#readme
Keywords: blame-g,git blame,git contributor stats
Classifier: Programming Language :: Python :: 3
Classifier: License :: OSI Approved :: MIT License
Classifier: Operating System :: OS Independent
Classifier: Intended Audience :: Developers
Classifier: Topic :: Software Development :: Version Control
Requires-Python: >=3.7
License-File: LICENSE
Requires-Dist: gitpython
Requires-Dist: rich
Dynamic: license-file
